{"expireTime":9007200873344143000,"key":"10ef545db0b450c6d8b4b86e7ca2c1a9","val":{"name":"IMAGE_PROCESSING","inputPaths":["D:/Resources/waqankiecolodge/src/images/youtube.png"],"outputDir":"D:/Resources/waqankiecolodge/public/static/2bb20cd8c83cf0a66a840e33d3084ed5","args":{"isLazy":false,"operations":[{"outputPath":"53973\\youtube.png","args":{"height":30,"width":30,"cropFocus":17,"toFormat":"png","fit":"cover"}},{"outputPath":"7ab40\\youtube.png","args":{"height":60,"width":60,"cropFocus":17,"toFormat":"png","fit":"cover"}},{"outputPath":"a8b52\\youtube.png","args":{"height":120,"width":120,"cropFocus":17,"toFormat":"png","fit":"cover"}}],"pluginOptions":{"base64Width":20,"forceBase64Format":"","useMozJpeg":false,"stripMetadata":true,"lazyImageGeneration":true,"defaultQuality":50,"failOnError":true,"plugins":[]}}}}