{"expireTime":9007200873513278000,"key":"69532215e12537c039a8d4f5659c080b","val":{"name":"IMAGE_PROCESSING","inputPaths":["C:/Users/Daniela/Desktop/waqanki/waqankiecolodge/src/aves/Green Hermit.jpeg"],"outputDir":"C:/Users/Daniela/Desktop/waqanki/waqankiecolodge/public/static/31d2ef83705a38adaaca4ddcd49d989b","args":{"isLazy":false,"operations":[{"outputPath":"e52ed\\Green Hermit.webp","args":{"height":212,"width":320,"cropFocus":17,"toFormat":"webp","fit":"cover"}},{"outputPath":"5699c\\Green Hermit.webp","args":{"height":423,"width":640,"cropFocus":17,"toFormat":"webp","fit":"cover"}},{"outputPath":"34422\\Green Hermit.webp","args":{"height":846,"width":1280,"cropFocus":17,"toFormat":"webp","fit":"cover"}}],"pluginOptions":{"base64Width":20,"forceBase64Format":"","useMozJpeg":false,"stripMetadata":true,"lazyImageGeneration":true,"defaultQuality":50,"failOnError":true,"plugins":[]}}}}