{"expireTime":9007200873513278000,"key":"a65206d8ed3d89e4243136d7e9f219e6","val":{"name":"IMAGE_PROCESSING","inputPaths":["C:/Users/Daniela/Desktop/waqanki/waqankiecolodge/src/aves/Canada warbler.JPG"],"outputDir":"C:/Users/Daniela/Desktop/waqanki/waqankiecolodge/public/static/9c6af46c0d986e98ff816a14c7f84a2e","args":{"isLazy":false,"operations":[{"outputPath":"b1a43\\Canada warbler.webp","args":{"height":229,"width":343,"cropFocus":17,"toFormat":"webp","fit":"cover"}},{"outputPath":"89678\\Canada warbler.webp","args":{"height":457,"width":685,"cropFocus":17,"toFormat":"webp","fit":"cover"}},{"outputPath":"0d7ab\\Canada warbler.webp","args":{"height":913,"width":1370,"cropFocus":17,"toFormat":"webp","fit":"cover"}}],"pluginOptions":{"base64Width":20,"forceBase64Format":"","useMozJpeg":false,"stripMetadata":true,"lazyImageGeneration":true,"defaultQuality":50,"failOnError":true,"plugins":[]}}}}