{"expireTime":9007200873513281000,"key":"ff28ae17ecb0cad6a26eb19ae6cc9762","val":{"name":"IMAGE_PROCESSING","inputPaths":["C:/Users/Daniela/Desktop/waqanki/waqankiecolodge/src/aves/Rufous-crested coquette 3.JPG"],"outputDir":"C:/Users/Daniela/Desktop/waqanki/waqankiecolodge/public/static/9a6d27d3bebe31ce8f95222919f0ea0d","args":{"isLazy":false,"operations":[{"outputPath":"eb59b\\Rufous-crested coquette 3.webp","args":{"height":498,"width":760,"cropFocus":17,"toFormat":"webp","fit":"cover"}},{"outputPath":"4f830\\Rufous-crested coquette 3.webp","args":{"height":996,"width":1521,"cropFocus":17,"toFormat":"webp","fit":"cover"}},{"outputPath":"52688\\Rufous-crested coquette 3.webp","args":{"height":1992,"width":3041,"cropFocus":17,"toFormat":"webp","fit":"cover"}}],"pluginOptions":{"base64Width":20,"forceBase64Format":"","useMozJpeg":false,"stripMetadata":true,"lazyImageGeneration":true,"defaultQuality":50,"failOnError":true,"plugins":[]}}}}