{"expireTime":9007200873513281000,"key":"9485597d4c224ab53e72998615026530","val":{"name":"IMAGE_PROCESSING","inputPaths":["C:/Users/Daniela/Desktop/waqanki/waqankiecolodge/src/aves/Great jacamar.JPG"],"outputDir":"C:/Users/Daniela/Desktop/waqanki/waqankiecolodge/public/static/be0e19eeb71adbacc84f13b04da26f44","args":{"isLazy":false,"operations":[{"outputPath":"9f054\\Great jacamar.jpg","args":{"height":521,"width":782,"cropFocus":17,"toFormat":"jpg","fit":"cover"}},{"outputPath":"b555d\\Great jacamar.jpg","args":{"height":1042,"width":1563,"cropFocus":17,"toFormat":"jpg","fit":"cover"}},{"outputPath":"d5f33\\Great jacamar.jpg","args":{"height":2084,"width":3126,"cropFocus":17,"toFormat":"jpg","fit":"cover"}}],"pluginOptions":{"base64Width":20,"forceBase64Format":"","useMozJpeg":false,"stripMetadata":true,"lazyImageGeneration":true,"defaultQuality":50,"failOnError":true,"plugins":[]}}}}