{"expireTime":9007200873344144000,"key":"c67065f671bdd1c4e64308af7d6cb03f","val":{"name":"IMAGE_PROCESSING","inputPaths":["D:/Resources/waqankiecolodge/src/aves/Stripe-necked tody-flycatcher.JPG"],"outputDir":"D:/Resources/waqankiecolodge/public/static/4987e0dba75db5eb901b248a63e4369c","args":{"isLazy":false,"operations":[{"outputPath":"cb333\\Stripe-necked tody-flycatcher.jpg","args":{"height":444,"width":677,"cropFocus":17,"toFormat":"jpg","fit":"cover"}},{"outputPath":"97ec0\\Stripe-necked tody-flycatcher.jpg","args":{"height":889,"width":1354,"cropFocus":17,"toFormat":"jpg","fit":"cover"}},{"outputPath":"f7d9c\\Stripe-necked tody-flycatcher.jpg","args":{"height":1777,"width":2707,"cropFocus":17,"toFormat":"jpg","fit":"cover"}}],"pluginOptions":{"base64Width":20,"forceBase64Format":"","useMozJpeg":false,"stripMetadata":true,"lazyImageGeneration":true,"defaultQuality":50,"failOnError":true,"plugins":[]}}}}